np_pipeline_qc/__init__.py
np_pipeline_qc/__main__.py
np_pipeline_qc/classes.py
np_pipeline_qc/legacy/__init__.py
np_pipeline_qc/legacy/align_physiology_plots.py
np_pipeline_qc/legacy/analysis.py
np_pipeline_qc/legacy/analyze_nwb.py
np_pipeline_qc/legacy/batch_copy_d2_files_for_LIMS_upload.py
np_pipeline_qc/legacy/batch_copy_d2_lims_files.py
np_pipeline_qc/legacy/batch_hab_qc.py
np_pipeline_qc/legacy/batch_lims_validation.py
np_pipeline_qc/legacy/batch_qc.py
np_pipeline_qc/legacy/batch_rf.py
np_pipeline_qc/legacy/batch_variability_qc.py
np_pipeline_qc/legacy/behavior_analysis.py
np_pipeline_qc/legacy/build_stim_tables.py
np_pipeline_qc/legacy/channel_visual_modulation.py
np_pipeline_qc/legacy/check_datacube.py
np_pipeline_qc/legacy/copy_d2_lims_files_for_upload.py
np_pipeline_qc/legacy/D1_LIMS_schema.py
np_pipeline_qc/legacy/D1_local_schema.py
np_pipeline_qc/legacy/D2_LIMS_schema.py
np_pipeline_qc/legacy/d2_upload_tool.py
np_pipeline_qc/legacy/data_getters.py
np_pipeline_qc/legacy/ebs_analysis.py
np_pipeline_qc/legacy/ebs_object_analysis.py
np_pipeline_qc/legacy/ecephys.py
np_pipeline_qc/legacy/EcephysBehaviorSession.py
np_pipeline_qc/legacy/get_probe_info.py
np_pipeline_qc/legacy/get_RFs_standalone.py
np_pipeline_qc/legacy/get_sessions.py
np_pipeline_qc/legacy/lims_validation.py
np_pipeline_qc/legacy/local_data_validation.py
np_pipeline_qc/legacy/nwb_validation_optotagging.py
np_pipeline_qc/legacy/probe_alignment_data_io.py
np_pipeline_qc/legacy/probe_track_day_assignment.py
np_pipeline_qc/legacy/probeSync_qc.py
np_pipeline_qc/legacy/qc_cmd_caller.py
np_pipeline_qc/legacy/query_lims.py
np_pipeline_qc/legacy/reformat_probe_annotation_files.py
np_pipeline_qc/legacy/run_qc_callable.py
np_pipeline_qc/legacy/run_qc_class.py
np_pipeline_qc/legacy/run_qc_modular.py
np_pipeline_qc/legacy/save_ecephysbehavior_session.py
np_pipeline_qc/legacy/sync_dataset.py
np_pipeline_qc/legacy/task1_behavior_session.py
np_pipeline_qc/legacy/update_probe_json.py
np_pipeline_qc-0.0.30.dist-info/WHEEL
np_pipeline_qc-0.0.30.dist-info/METADATA
np_pipeline_qc-0.0.30.dist-info/RECORD
