Metadata-Version: 2.1
Name: np_pipeline_qc
Version: 0.0.30
Summary: Analysis and visualization code for quality-control of Neuropixels pipeline data.
Author-email: corbennett <corbettb@alleninstitute.org>
Maintainer-email: bjhardcastle <ben.hardcastle@alleninstitute.org>
Requires-Python: >=3.8
Classifier: License :: OSI Approved :: MIT License
Classifier: Operating System :: Microsoft :: Windows
Classifier: Programming Language :: Python :: 3
Classifier: Programming Language :: Python :: 3.10
Classifier: Programming Language :: Python :: 3.11
Classifier: Programming Language :: Python :: 3.8
Classifier: Programming Language :: Python :: 3.9
Requires-Dist: async-timeout<4.0
Requires-Dist: beautifulsoup4
Requires-Dist: cmake>=3.26.3
Requires-Dist: importlib-resources>=5.12.0
Requires-Dist: np-session>=0.6.38
Requires-Dist: np-tools>=0.1.20
Requires-Dist: np-vba>=0.13.1
Requires-Dist: numba
Requires-Dist: setuptools
Provides-Extra: dev
Requires-Dist: np_pipeline_qc[html]; extra == "dev"
Requires-Dist: isort; extra == "dev"
Requires-Dist: mypy; extra == "dev"
Requires-Dist: pytest; extra == "dev"
Requires-Dist: pytest-cov; extra == "dev"
Requires-Dist: blue>=0.9.1; extra == "dev"
Requires-Dist: coverage[toml]>=7.2.2; extra == "dev"
Requires-Dist: pdm>=2.4.9; extra == "dev"
Requires-Dist: bump>=1.3.2; extra == "dev"
Requires-Dist: types-backports>=0.1.3; extra == "dev"
Requires-Dist: ruff>=0.0.260; extra == "dev"
